<?xml version="1.0" encoding="UTF-8"?><artifacts>
    <artifact name="fileSplitAPI" groupId="com.example.api" version="1.0.0" type="synapse/api" serverRole="EnterpriseServiceBus">
        <file>src/main/synapse-config/api/fileSplitAPI.xml</file>
    </artifact>
    <artifact name="fileSplitAPI_swagger" groupId="com.example.metadata" version="1.0.0" type="synapse/metadata" serverRole="EnterpriseServiceBus">
        <file>src/main/resources/metadata/fileSplitAPI_swagger.yaml</file>
    </artifact>
    <artifact name="fileSplitAPI_metadata" groupId="com.example.metadata" version="1.0.0" type="synapse/metadata" serverRole="EnterpriseServiceBus">
        <file>src/main/resources/metadata/fileSplitAPI_metadata.yaml</file>
    </artifact>
    <artifact name="file_connect" groupId="com.example.local-entry" version="1.0.0" type="synapse/local-entry" serverRole="EnterpriseServiceBus">
        <file>\src\main\synapse-config\local-entries\file_connect.xml</file>
    </artifact>
</artifacts>
